[
  {
    "id": "9dab8c52-849d-48df-9399-476486bb10f3",
    "name": "Brose à cheveux",
    "description": "Super outils pour avoir une belle coupe",
    "price": "22",
    "stock": "120",
    "created_at": "31/03/2022, 11:18:12",
    "updated_at": "31/03/2022, 11:18:12"
  },
  {
    "id": "cfc07f06-4127-47e3-9b18-6021e4c0e40b",
    "name": "Super lampe frontale",
    "description": "Pratique la nuit",
    "price": "9.99",
    "stock": "68",
    "created_at": "31/03/2022, 12:04:04",
    "updated_at": "31/03/2022, 12:07:55"
  },
  {
    "id": "cfc07f06-4127-47c3-9a18-6021e4c0e40b",
    "name": "Bouteille Perrier test",
    "description": "Bouteille d'eau pétillante",
    "price": "3.2",
    "stock": "340",
    "created_at": "04/05/2022, 16:43:12",
    "updated_at": "04/05/2022, 16:50:52"
  }
]